fractal_input/__init__.py
fractal_input/constraint.py
fractal_input/input_handler.py
fractal_input/node.py
fractal_input/type_handler.py
fractal_input/version.py
fractal_input-2.1.0.dist-info/METADATA
fractal_input-2.1.0.dist-info/WHEEL
fractal_input-2.1.0.dist-info/entry_points.txt
fractal_input-2.1.0.dist-info/top_level.txt
fractal_input-2.1.0.dist-info/RECORD
